gotopub/__init__.py
gotopub/__main__.py
gotopub/version.py
gotopub-0.0.2.dist-info/LICENSE
gotopub-0.0.2.dist-info/METADATA
gotopub-0.0.2.dist-info/WHEEL
gotopub-0.0.2.dist-info/entry_points.txt
gotopub-0.0.2.dist-info/top_level.txt
gotopub-0.0.2.dist-info/RECORD
