Metadata-Version: 2.1
Name: gotopub
Version: 0.0.2
Summary: gotopub - GoToSocial and general Fediverse client
Home-page: https://gitlab.com/sunarch/gotopub-py
Author: András Németh (sunarch)
Author-email: sunarch@protonmail.com
Maintainer: András Németh (sunarch)
Maintainer-email: sunarch@protonmail.com
License: GNU Affero General Public License v3 or later (AGPLv3+)
Project-URL: Bug Tracker, https://gitlab.com/sunarch/gotopub-py/-/issues
Keywords: GoToPub,Fediverse,ActivityPub,GoToSocial,Mastodon
Platform: Any
Classifier: Development Status :: 1 - Planning
Classifier: Environment :: Console
Classifier: Environment :: Web Environment
Classifier: Framework :: Flask
Classifier: Intended Audience :: End Users/Desktop
Classifier: License :: OSI Approved :: GNU Affero General Public License v3 or later (AGPLv3+)
Classifier: Operating System :: OS Independent
Classifier: Programming Language :: Python :: 3
Classifier: Topic :: Communications
Classifier: Topic :: Database :: Front-Ends
Classifier: Topic :: Internet :: WWW/HTTP :: Dynamic Content
Classifier: Topic :: Office/Business :: News/Diary
Classifier: Topic :: System :: Networking
Classifier: Typing :: Typed
Requires-Python: >=3.10
License-File: LICENSE
Requires-Dist: libmonty-logging ==0.1.1
Requires-Dist: xdg-base-dirs ==6.0.0
